pepperize_cdk_security_group/__init__.py
pepperize_cdk_security_group/py.typed
pepperize_cdk_security_group/_jsii/__init__.py
pepperize_cdk_security_group/_jsii/cdk-security-group@0.0.662.jsii.tgz
pepperize_cdk_security_group-0.0.662.dist-info/LICENSE
pepperize_cdk_security_group-0.0.662.dist-info/METADATA
pepperize_cdk_security_group-0.0.662.dist-info/WHEEL
pepperize_cdk_security_group-0.0.662.dist-info/top_level.txt
pepperize_cdk_security_group-0.0.662.dist-info/RECORD
